brep_part_finder/__init__.py
brep_part_finder/_version.py
brep_part_finder/core.py
brep_part_finder-0.5.2.dist-info/LICENSE.txt
brep_part_finder-0.5.2.dist-info/METADATA
brep_part_finder-0.5.2.dist-info/WHEEL
brep_part_finder-0.5.2.dist-info/top_level.txt
brep_part_finder-0.5.2.dist-info/RECORD
