Metadata-Version: 2.1
Name: brep-part-finder
Version: 0.5.2
Summary: A Python package to identify the part ID number in Brep format CAD files
Author-email: Jonathan Shimwell <mail@jshimwell.com>
License: MIT License
Project-URL: Homepage, https://github.com/fusion-energy/brep_part_finder
Project-URL: Bug Tracker, https://github.com/fusion-energy/brep_part_finder/issues
Keywords: brep,geometry,part,find,identify,volume
Classifier: Programming Language :: Python :: 3
Classifier: License :: OSI Approved :: MIT License
Classifier: Operating System :: OS Independent
Requires-Python: >=3.8
License-File: LICENSE.txt
Requires-Dist: numpy (>=1.21.1)
Provides-Extra: tests
Requires-Dist: pytest ; extra == 'tests'
